setup.py
cellar_management/__init__.py
cellar_management/bottle.py
cellar_management/cellar.py
cellar_management.egg-info/PKG-INFO
cellar_management.egg-info/SOURCES.txt
cellar_management.egg-info/dependency_links.txt
cellar_management.egg-info/not-zip-safe
cellar_management.egg-info/top_level.txt