Metadata-Version: 1.0
Name: cellar-management
Version: 1.0
Summary: Simple cellar management tool
Home-page: UNKNOWN
Author: Julien Flandre
Author-email: julien.flandre@gmail.com
License: UNKNOWN
Platform: UNKNOWN
